fds/__init__.py
fds/sdk/__init__.py
fds/sdk/IRNMeetings/__init__.py
fds/sdk/IRNMeetings/api_client.py
fds/sdk/IRNMeetings/configuration.py
fds/sdk/IRNMeetings/exceptions.py
fds/sdk/IRNMeetings/model_utils.py
fds/sdk/IRNMeetings/rest.py
fds/sdk/IRNMeetings/api/__init__.py
fds/sdk/IRNMeetings/api/attachments_api.py
fds/sdk/IRNMeetings/api/comments_api.py
fds/sdk/IRNMeetings/api/events_api.py
fds/sdk/IRNMeetings/api/meetings_api.py
fds/sdk/IRNMeetings/apis/__init__.py
fds/sdk/IRNMeetings/model/__init__.py
fds/sdk/IRNMeetings/model/attachment_summary_dto.py
fds/sdk/IRNMeetings/model/attendee_dto.py
fds/sdk/IRNMeetings/model/comment_dto.py
fds/sdk/IRNMeetings/model/comment_summary_dto.py
fds/sdk/IRNMeetings/model/create_body_dto.py
fds/sdk/IRNMeetings/model/create_comment_dto.py
fds/sdk/IRNMeetings/model/create_custom_field_value_dto.py
fds/sdk/IRNMeetings/model/create_meeting_dto.py
fds/sdk/IRNMeetings/model/custom_field_value_dto.py
fds/sdk/IRNMeetings/model/location_dto.py
fds/sdk/IRNMeetings/model/meeting_dto.py
fds/sdk/IRNMeetings/model/meeting_event_dto.py
fds/sdk/IRNMeetings/model/meeting_summary_dto.py
fds/sdk/IRNMeetings/model/new_item_dto.py
fds/sdk/IRNMeetings/model/operation.py
fds/sdk/IRNMeetings/model/operation_type.py
fds/sdk/IRNMeetings/model/problem_details.py
fds/sdk/IRNMeetings/model/record_change_dto.py
fds/sdk/IRNMeetings/model/record_event_summary_dto.py
fds/sdk/IRNMeetings/model/reference_attendee_dto.py
fds/sdk/IRNMeetings/model/related_records_dto.py
fds/sdk/IRNMeetings/model/subcomment_summary_dto.py
fds/sdk/IRNMeetings/model/update_meeting_dto.py
fds/sdk/IRNMeetings/model/user_serial_dto.py
fds/sdk/IRNMeetings/model/user_team_lookup_dto.py
fds/sdk/IRNMeetings/models/__init__.py
fds.sdk.IRNMeetings-2.0.2.dist-info/LICENSE
fds.sdk.IRNMeetings-2.0.2.dist-info/METADATA
fds.sdk.IRNMeetings-2.0.2.dist-info/WHEEL
fds.sdk.IRNMeetings-2.0.2.dist-info/top_level.txt
fds.sdk.IRNMeetings-2.0.2.dist-info/RECORD
